README.txt
setup.py
subzilla/__init__.py
subzilla/subzilla.py
subzilla.egg-info/SOURCES.txt
