Metadata-Version: 1.0
Name: subzilla
Version: 0.2.2
Summary: Subzilla will post a patch from a Subversion tree to a Bugzilla 3.0 bug, or apply a patch from a Bugzilla bug to a Subversion tree.
Home-page: http://svn.osafoundation.org/sandbox/jeffrey/subzilla/README.txt
Author: Jeffrey Harris
Author-email: UNKNOWN
License: UNKNOWN
Platform: UNKNOWN
Classifier: Development Status :: 3 - Alpha
Classifier: Environment :: Console
Classifier: Environment :: Web Environment
Classifier: Intended Audience :: Developers
Classifier: License :: OSI Approved :: Python Software Foundation License
Classifier: Programming Language :: Python
Classifier: Topic :: Software Development :: Bug Tracking
